tests/__init__.py
tests/test_acquisition.py
tests/test_acquisition_optimiser.py
tests/test_constructors.py
tests/test_kernels.py
tests/test_model.py
tests/test_normaliser.py
tests/test_optimiser.py
tests/test_optimiser_saver_loader.py
tests/test_optimiser_utility.py
tests/test_prediction.py
tests/test_saver_loader_utility.py
veropt/__init__.py
veropt/py.typed
veropt/graphical/__init__.py
veropt/graphical/_model_visualisation.py
veropt/graphical/_overview.py
veropt/graphical/_pareto_front.py
veropt/graphical/_visualisation_utility.py
veropt/graphical/visualisation.py
veropt/interfaces/__init__.py
veropt/interfaces/batch_manager.py
veropt/interfaces/constructors.py
veropt/interfaces/experiment.py
veropt/interfaces/experiment_utility.py
veropt/interfaces/local_simulation.py
veropt/interfaces/result_processing.py
veropt/interfaces/simulation.py
veropt/interfaces/slurm_simulation.py
veropt/interfaces/utility.py
veropt/interfaces/veros_utility.py
veropt/optimiser/__init__.py
veropt/optimiser/acquisition.py
veropt/optimiser/acquisition_optimiser.py
veropt/optimiser/constructors.py
veropt/optimiser/default_settings.json
veropt/optimiser/initial_points.py
veropt/optimiser/kernels.py
veropt/optimiser/model.py
veropt/optimiser/normalisation.py
veropt/optimiser/objective.py
veropt/optimiser/optimiser.py
veropt/optimiser/optimiser_saver_loader.py
veropt/optimiser/optimiser_utility.py
veropt/optimiser/practice_objectives.py
veropt/optimiser/prediction.py
veropt/optimiser/saver_loader_utility.py
veropt/optimiser/utility.py
veropt-1.2.0.dist-info/licenses/LICENSE
veropt-1.2.0.dist-info/METADATA
veropt-1.2.0.dist-info/WHEEL
veropt-1.2.0.dist-info/top_level.txt
veropt-1.2.0.dist-info/RECORD
