Metadata-Version: 2.4
Name: veropt
Version: 1.2.0
Summary: User-friendly Bayesian Optimisation for computationally expensive problems
Home-page: https://github.com/aster-stoustrup/veropt
Author: Aster Stoustrup
Author-email: aster.stoustrup@gmail.com
License: OSI Approved :: GNU General Public License v3 or later (GPLv3+)
Requires-Python: >3.13
License-File: LICENSE
Requires-Dist: numpy
Requires-Dist: torch
Requires-Dist: gpytorch
Requires-Dist: botorch
Requires-Dist: dill
Requires-Dist: scipy
Requires-Dist: plotly
Requires-Dist: kaleido
Requires-Dist: dash
Requires-Dist: pydantic
Requires-Dist: xarray
Requires-Dist: tqdm
Dynamic: author
Dynamic: author-email
Dynamic: description
Dynamic: description-content-type
Dynamic: home-page
Dynamic: license
Dynamic: license-file
Dynamic: requires-dist
Dynamic: requires-python
Dynamic: summary
